warden_sdk/__init__.py
warden_sdk/_compat.py
warden_sdk/_functools.py
warden_sdk/_queue.py
warden_sdk/api.py
warden_sdk/attachments.py
warden_sdk/auth/__init__.py
warden_sdk/auth/exceptions.py
warden_sdk/auth/headers.py
warden_sdk/auth/oauth.py
warden_sdk/auth/scope_guard.py
warden_sdk/auth/user.py
warden_sdk/client.py
warden_sdk/consts.py
warden_sdk/debug.py
warden_sdk/envelope.py
warden_sdk/hub.py
warden_sdk/integrations/__init__.py
warden_sdk/integrations/_wsgi_common.py
warden_sdk/integrations/argv.py
warden_sdk/integrations/asgi.py
warden_sdk/integrations/atexit.py
warden_sdk/integrations/awslambda.py
warden_sdk/integrations/boto3.py
warden_sdk/integrations/dedupe.py
warden_sdk/integrations/excepthook.py
warden_sdk/integrations/executing.py
warden_sdk/integrations/fastapi.py
warden_sdk/integrations/flask.py
warden_sdk/integrations/logging.py
warden_sdk/integrations/modules.py
warden_sdk/integrations/serverless.py
warden_sdk/integrations/starlette.py
warden_sdk/integrations/stdlib.py
warden_sdk/integrations/threading.py
warden_sdk/integrations/wsgi.py
warden_sdk/profiler.py
warden_sdk/py.tyed
warden_sdk/scope.py
warden_sdk/serializer.py
warden_sdk/session.py
warden_sdk/sessions.py
warden_sdk/tracing.py
warden_sdk/tracing_utils.py
warden_sdk/transport.py
warden_sdk/utils.py
warden_sdk/worker.py
warden_sdk-2.4.6.dist-info/LICENSE.md
warden_sdk-2.4.6.dist-info/WHEEL
warden_sdk-2.4.6.dist-info/METADATA
warden_sdk-2.4.6.dist-info/RECORD
