Metadata-Version: 2.1
Name: warden-sdk
Version: 2.4.6
Summary: 
Author: Ferant Tech Corp.
Author-email: cto@ferant.io
Requires-Python: >=3.8,<4.0
Classifier: Programming Language :: Python :: 3
Classifier: Programming Language :: Python :: 3.10
Classifier: Programming Language :: Python :: 3.8
Classifier: Programming Language :: Python :: 3.9
Requires-Dist: requests (>=2.28.1,<3.0.0)
Requires-Dist: tldextract (>=3.3.1,<4.0.0)
